clingcon/clingcon.h
clingcon/__init__.py
clingcon/__main__.py
clingcon/_clingcon.cpython-38-x86_64-linux-gnu.so
clingcon/py.typed
clingcon-5.2.1.post2.dist-info/WHEEL
clingcon-5.2.1.post2.dist-info/METADATA
clingcon-5.2.1.post2.dist-info/LICENSE.md
clingcon-5.2.1.post2.dist-info/top_level.txt
clingcon-5.2.1.post2.dist-info/RECORD
