Metadata-Version: 2.1
Name: clingcon
Version: 5.2.1.post2
Summary: CFFI-based bindings to the clingcon solver.
Home-page: https://github.com/potassco/clingcon
Author: Roland Kaminski
Author-email: kaminski@cs.uni-potsdam.de
License: MIT
Requires-Python: >=3.6
License-File: LICENSE.md
Requires-Dist: cffi
Requires-Dist: clingo
